{
	"class" : {
		"initialize" : "RS 7/10/2020 14:08",
		"open" : "RK 5/30/2022 20:33",
		"savedPins" : "RK 6/20/2022 21:30",
		"savedPins:" : "RK 6/20/2022 21:24",
		"thunderforestMapsApiKey" : "RS 6/20/2020 17:21",
		"thunderforestMapsApiKey:" : "RS 5/27/2020 09:33" },
	"instance" : {
		"apiKeyManagement" : "RS 8/2/2020 14:14",
		"apiKeyManagementOptions" : "ros 7/13/2022 21:19",
		"apiSelectionOptions" : "dn 8/6/2020 15:35",
		"bingApi" : "ros 7/13/2022 19:52",
		"bingApi:" : "ros 7/13/2022 19:52",
		"build" : "RK 5/30/2022 20:34",
		"buildDirectionsBikeButton:" : "RK 6/28/2022 11:36",
		"buildDirectionsCancelButton:" : "RK 7/13/2022 17:08",
		"buildDirectionsCarButton:" : "RK 6/28/2022 11:36",
		"buildDirectionsDestinationInput:" : "RK 7/13/2022 16:40",
		"buildDirectionsInputField:withAccessors:and:" : "RK 7/13/2022 16:33",
		"buildDirectionsLabel:with:" : "TR 6/8/2022 13:38",
		"buildDirectionsLabel:with:byPosition:" : "TR 6/8/2022 13:38",
		"buildDirectionsRouteInformation:" : "RK 7/13/2022 16:46",
		"buildDirectionsStartInput:" : "RK 7/13/2022 16:40",
		"buildDirectionsTopRow:" : "TR 6/8/2022 13:30",
		"buildDirectionsWalkButton:" : "RK 6/28/2022 11:36",
		"buildManageAPIKeysButton:" : "TR 6/8/2022 13:36",
		"buildMap:" : "RK 5/28/2022 19:45",
		"buildPinsButton:" : "RK 6/20/2022 15:38",
		"buildSearchInputField:" : "RK 7/13/2022 16:23",
		"buildSearchPinPanel:" : "TR 7/19/2022 14:21",
		"buildSearchPinPanelChildren" : "RK 6/20/2022 15:12",
		"buildSearchPinPanelDirectionsButton:" : "RK 6/20/2022 22:12",
		"buildSearchPinPanelLabel:" : "TR 7/19/2022 14:21",
		"buildSearchPinPanelRemovePinButton:" : "RK 6/20/2022 22:12",
		"buildSearchPinPanelSavePinButton:" : "RK 6/20/2022 22:12",
		"buildSelectAPIButton:" : "TR 6/8/2022 13:37",
		"buildSidebar:" : "ros 6/11/2022 22:32",
		"buildSidebarBottom:" : "TR 6/8/2022 13:34",
		"buildSidebarDirectionsChildren:" : "RK 7/13/2022 16:31",
		"buildSidebarSearchChildren:" : "RK 7/13/2022 16:10",
		"buildSidebarTop:" : "RK 5/28/2022 20:18",
		"buildSidebarTopChildren" : "TR 6/8/2022 13:37",
		"buildWith:" : "TR 6/8/2022 13:37",
		"checkBingApiKey" : "ros 7/13/2022 21:22",
		"checkThunderforestMapsApiKey" : "ros 7/13/2022 21:33",
		"currentView" : "TR 6/25/2022 14:11",
		"currentView:" : "TR 6/25/2022 14:12",
		"destinationSearchInput" : "TR 6/25/2022 14:12",
		"destinationSearchInput:" : "TR 7/6/2022 11:23",
		"getDestinationLabel" : "RK 5/29/2022 12:42",
		"getDistanceLabel" : "TR 7/6/2022 13:43",
		"getDurationLabel" : "TR 7/8/2022 09:12",
		"getMapMorph" : "TR 6/17/2022 09:37",
		"getPinLabel" : "RK 6/15/2022 21:14",
		"getStartLabel" : "RK 5/29/2022 12:42",
		"hasModeBike" : "RK 6/28/2022 11:35",
		"hasModeCar" : "RK 6/28/2022 11:35",
		"hasModeWalk" : "RK 6/28/2022 11:35",
		"hasSearched" : "TR 6/25/2022 14:14",
		"hasSearched:" : "TR 6/25/2022 14:14",
		"informInvalidKey" : "dn 8/6/2020 15:41",
		"initialize" : "TR 7/21/2022 08:26",
		"isSelectedPinSaved" : "TR 7/19/2022 15:43",
		"mapConfigurator" : "TR 6/25/2022 12:48",
		"mapConfigurator:" : "TR 6/25/2022 12:48",
		"removePin" : "TR 7/19/2022 15:43",
		"requestApiSelection" : "RS 8/2/2020 14:15",
		"requestBingApiKeyInput" : "ros 7/13/2022 21:23",
		"requestOpenrouteserviceApiKeyInput" : "TR 6/25/2022 11:35",
		"requestSavedPinSelection" : "TR 7/20/2022 08:26",
		"requestThunderforestApiKeyInput" : "ros 7/13/2022 21:33",
		"route" : "TR 7/6/2022 13:43",
		"route:" : "TR 7/8/2022 09:31",
		"savePin" : "RK 6/20/2022 21:37",
		"searchDirections" : "TR 7/21/2022 18:10",
		"searchInput" : "TR 6/25/2022 14:15",
		"searchInput:" : "RK 7/13/2022 16:21",
		"searchLocation" : "RK 7/18/2022 15:22",
		"searchLocationFromCoordinates:" : "TR 7/20/2022 11:32",
		"searchManager" : "TR 6/25/2022 14:15",
		"searchManager:" : "TR 6/25/2022 14:16",
		"selectedPin" : "RK 6/10/2022 20:54",
		"selectedPin:" : "TR 7/8/2022 09:33",
		"setBingAsApiWith:" : "ros 7/13/2022 20:21",
		"setDestinationSearchInput" : "TR 6/16/2022 18:55",
		"setOpenstreetmapsAsApi" : "cs 8/4/2020 14:45",
		"setSelectedPin:" : "RK 7/13/2022 17:01",
		"setThunderforestAsApiWith:" : "ros 7/13/2022 20:39",
		"showPin" : "RK 7/13/2022 17:56",
		"startSearchInput" : "TR 6/25/2022 14:16",
		"startSearchInput:" : "TR 7/6/2022 11:24",
		"submitDestinationSearchInput:" : "RK 7/13/2022 16:32",
		"submitSearchInput:" : "RK 7/13/2022 16:23",
		"submitStartSearchInput:" : "RK 7/13/2022 16:32",
		"switchToDirectionsView" : "RK 7/13/2022 17:18",
		"switchToEmptySearchView" : "RK 7/13/2022 17:52",
		"switchToModeBike" : "LK 6/28/2022 17:16",
		"switchToModeCar" : "LK 6/28/2022 17:16",
		"switchToModeWalk" : "LK 6/28/2022 17:16",
		"switchToSearchView" : "RK 7/13/2022 17:07",
		"switchToSearchViewWith:" : "RK 7/13/2022 17:07",
		"thunderforestMapsApi" : "ros 7/13/2022 20:31",
		"thunderforestMapsApi:" : "ros 7/13/2022 20:31",
		"tiledMapMorph" : "dn 8/6/2020 15:37",
		"tiledMapMorph:" : "TR 6/25/2022 14:17",
		"transportationModeInput" : "TR 6/25/2022 14:17",
		"transportationModeInput:" : "TR 6/25/2022 14:17" } }
